Metadata-Version: 2.1
Name: pedia-cloud
Version: 0.0.11
Summary: A third-party Python API for Pedia Cloud Dictionary
Home-page: https://github.com/sheiun/pedia-cloud
Author: SheiUn
Author-email: develop@sheiun.me
License: UNKNOWN
Platform: UNKNOWN
Classifier: Programming Language :: Python :: 3
Classifier: License :: OSI Approved :: MIT License
Classifier: Operating System :: OS Independent
Requires-Python: >=3.7
